LICENSE
README.md
setup.cfg
setup.py
dddes.egg-info/PKG-INFO
dddes.egg-info/SOURCES.txt
dddes.egg-info/dependency_links.txt
dddes.egg-info/requires.txt
dddes.egg-info/top_level.txt
python_ddd/__init__.py
python_ddd/domain/Entity.py
python_ddd/domain/Identity.py
python_ddd/domain/ValueObject.py
python_ddd/domain/__init__.py
python_ddd/eventsourcing/DomainEventListener.py
python_ddd/eventsourcing/DomainObject.py
python_ddd/eventsourcing/EventSourceRepository.py
python_ddd/eventsourcing/Projection.py
python_ddd/eventsourcing/__init__.py